siqadtools-0.2.2.dist-info/METADATA
siqadtools-0.2.2.dist-info/top_level.txt
siqadtools-0.2.2.dist-info/RECORD
siqadtools-0.2.2.dist-info/WHEEL
siqadtools-0.2.2.dist-info/LICENSE
siqadtools/__init__.py
siqadtools/siqadconn.py
siqadtools/_siqadconn.so
